scrapli_cfg/__init__.py
scrapli_cfg/diff.py
scrapli_cfg/exceptions.py
scrapli_cfg/factory.py
scrapli_cfg/helper.py
scrapli_cfg/logging.py
scrapli_cfg/py.typed
scrapli_cfg/response.py
scrapli_cfg/platform/__init__.py
scrapli_cfg/platform/base/__init__.py
scrapli_cfg/platform/base/async_platform.py
scrapli_cfg/platform/base/base_platform.py
scrapli_cfg/platform/base/sync_platform.py
scrapli_cfg/platform/core/__init__.py
scrapli_cfg/platform/core/arista_eos/__init__.py
scrapli_cfg/platform/core/arista_eos/async_platform.py
scrapli_cfg/platform/core/arista_eos/base_platform.py
scrapli_cfg/platform/core/arista_eos/patterns.py
scrapli_cfg/platform/core/arista_eos/sync_platform.py
scrapli_cfg/platform/core/cisco_iosxe/__init__.py
scrapli_cfg/platform/core/cisco_iosxe/async_platform.py
scrapli_cfg/platform/core/cisco_iosxe/base_platform.py
scrapli_cfg/platform/core/cisco_iosxe/patterns.py
scrapli_cfg/platform/core/cisco_iosxe/sync_platform.py
scrapli_cfg/platform/core/cisco_iosxr/__init__.py
scrapli_cfg/platform/core/cisco_iosxr/async_platform.py
scrapli_cfg/platform/core/cisco_iosxr/base_platform.py
scrapli_cfg/platform/core/cisco_iosxr/patterns.py
scrapli_cfg/platform/core/cisco_iosxr/sync_platform.py
scrapli_cfg/platform/core/cisco_nxos/__init__.py
scrapli_cfg/platform/core/cisco_nxos/async_platform.py
scrapli_cfg/platform/core/cisco_nxos/base_platform.py
scrapli_cfg/platform/core/cisco_nxos/patterns.py
scrapli_cfg/platform/core/cisco_nxos/sync_platform.py
scrapli_cfg/platform/core/juniper_junos/__init__.py
scrapli_cfg/platform/core/juniper_junos/async_platform.py
scrapli_cfg/platform/core/juniper_junos/base_platform.py
scrapli_cfg/platform/core/juniper_junos/patterns.py
scrapli_cfg/platform/core/juniper_junos/sync_platform.py
scrapli_cfg-2025.1.30.dist-info/LICENSE
scrapli_cfg-2025.1.30.dist-info/METADATA
scrapli_cfg-2025.1.30.dist-info/WHEEL
scrapli_cfg-2025.1.30.dist-info/top_level.txt
scrapli_cfg-2025.1.30.dist-info/RECORD
