Metadata-Version: 2.2
Name: scrapli_cfg
Version: 2025.1.30
Summary: Network device configuration management with scrapli
Author-email: Carl Montanari <carl.r.montanari@gmail.com>
License: MIT License
Project-URL: Changelog, https://scrapli.github.io/scrapli_cfg/changelog/
Project-URL: Docs, https://scrapli.github.io/scrapli_cfg/
Project-URL: Homepage, https://github.com/scrapli/scrapli_cfg
Keywords: arista,automation,cisco,eos,iosxe,iosxr,juniper,junos,netconf,network,nxos,ssh,telnet
Classifier: License :: OSI Approved :: MIT License
Classifier: Operating System :: POSIX :: Linux
Classifier: Operating System :: MacOS
Classifier: Programming Language :: Python
Classifier: Programming Language :: Python :: 3.9
Classifier: Programming Language :: Python :: 3.10
Classifier: Programming Language :: Python :: 3.11
Classifier: Programming Language :: Python :: 3.12
Classifier: Programming Language :: Python :: 3.13
Classifier: Programming Language :: Python :: 3 :: Only
Classifier: Topic :: Software Development :: Libraries :: Python Modules
Requires-Python: >=3.9
License-File: LICENSE
Requires-Dist: scrapli>=2022.01.30a2
Provides-Extra: dev-darwin
Requires-Dist: black<25.0.0,>=23.3.0; extra == "dev-darwin"
Requires-Dist: darglint<2.0.0,>=1.8.1; extra == "dev-darwin"
Requires-Dist: isort<6.0.0,>=5.10.1; extra == "dev-darwin"
Requires-Dist: mypy<2.0.0,>=1.4.1; extra == "dev-darwin"
Requires-Dist: nox==2024.4.15; extra == "dev-darwin"
Requires-Dist: pydocstyle<7.0.0,>=6.1.1; extra == "dev-darwin"
Requires-Dist: pyfakefs<6.0.0,>=5.4.1; extra == "dev-darwin"
Requires-Dist: pylint<4.0.0,>=3.0.0; extra == "dev-darwin"
Requires-Dist: pytest-asyncio<1.0.0,>=0.17.0; extra == "dev-darwin"
Requires-Dist: pytest-cov<5.0.0,>=3.0.0; extra == "dev-darwin"
Requires-Dist: pytest<8.0.0,>=7.0.0; extra == "dev-darwin"
Requires-Dist: scrapli-replay==2023.7.30; extra == "dev-darwin"
Requires-Dist: toml<1.0.0,>=0.10.2; extra == "dev-darwin"
Requires-Dist: paramiko<4.0.0,>=2.6.0; extra == "dev-darwin"
Requires-Dist: asyncssh<3.0.0,>=2.2.1; extra == "dev-darwin"
Provides-Extra: dev
Requires-Dist: black<25.0.0,>=23.3.0; extra == "dev"
Requires-Dist: darglint<2.0.0,>=1.8.1; extra == "dev"
Requires-Dist: isort<6.0.0,>=5.10.1; extra == "dev"
Requires-Dist: mypy<2.0.0,>=1.4.1; extra == "dev"
Requires-Dist: nox==2024.4.15; extra == "dev"
Requires-Dist: pydocstyle<7.0.0,>=6.1.1; extra == "dev"
Requires-Dist: pyfakefs<6.0.0,>=5.4.1; extra == "dev"
Requires-Dist: pylint<4.0.0,>=3.0.0; extra == "dev"
Requires-Dist: pytest-asyncio<1.0.0,>=0.17.0; extra == "dev"
Requires-Dist: pytest-cov<5.0.0,>=3.0.0; extra == "dev"
Requires-Dist: pytest<8.0.0,>=7.0.0; extra == "dev"
Requires-Dist: scrapli-replay==2023.7.30; extra == "dev"
Requires-Dist: toml<1.0.0,>=0.10.2; extra == "dev"
Requires-Dist: paramiko<4.0.0,>=2.6.0; extra == "dev"
Requires-Dist: ssh2-python<2.0.0,>=0.23.0; python_version < "3.12" and extra == "dev"
Requires-Dist: asyncssh<3.0.0,>=2.2.1; extra == "dev"
Provides-Extra: docs
Requires-Dist: mdx-gh-links<1.0,>=0.2; extra == "docs"
Requires-Dist: mkdocs<2.0.0,>=1.2.3; extra == "docs"
Requires-Dist: mkdocs-gen-files<1.0.0,>=0.4.0; extra == "docs"
Requires-Dist: mkdocs-literate-nav<1.0.0,>=0.5.0; extra == "docs"
Requires-Dist: mkdocs-material<10.0.0,>=8.1.6; extra == "docs"
Requires-Dist: mkdocs-material-extensions<2.0.0,>=1.0.3; extra == "docs"
Requires-Dist: mkdocs-section-index<1.0.0,>=0.3.4; extra == "docs"
Requires-Dist: mkdocstrings[python]<1.0.0,>=0.19.0; extra == "docs"
Provides-Extra: paramiko
Requires-Dist: paramiko<4.0.0,>=2.6.0; extra == "paramiko"
Provides-Extra: ssh2
Requires-Dist: ssh2-python<2.0.0,>=0.23.0; python_version < "3.12" and extra == "ssh2"
Provides-Extra: asyncssh
Requires-Dist: asyncssh<3.0.0,>=2.2.1; extra == "asyncssh"
